booleanfix/__init__.py
booleanfix-1.2.0.dist-info/LICENSE
booleanfix-1.2.0.dist-info/METADATA
booleanfix-1.2.0.dist-info/WHEEL
booleanfix-1.2.0.dist-info/top_level.txt
booleanfix-1.2.0.dist-info/RECORD
