Metadata-Version: 2.1
Name: booleanfix
Version: 1.2.0
Summary: Fix for boolean variables in Python
Home-page: https://github.com/EDM115/booleanfix
Author: EDM115
Author-email: EDM115 <dev@edm115.eu.org>
License: MIT License
Project-URL: Homepage, https://github.com/EDM115/booleanfix
Project-URL: Bug Tracker, https://github.com/EDM115/booleanfix/issues
Project-URL: Funding, https://github.com/EDM115#support-me-
Keywords: boolean,fix,python
Classifier: Development Status :: 5 - Production/Stable
Classifier: Intended Audience :: Developers
Classifier: Topic :: Software Development
Classifier: License :: OSI Approved :: MIT License
Classifier: Programming Language :: Python :: 2
Classifier: Programming Language :: Python :: 3
License-File: LICENSE
